{
  "students": [
    {
      "id": "eHkz4Ll",
      "studentName": "Tejaswini",
      "category": "Domestic",
      "domicileDoc": true,
      "birthDoc": true,
      "marksheetDoc": true,
      "policeClearanceDoc": true,
      "passportDoc": true,
      "declarationDoc": true,
      "dob": "1999-08-28",
      "fathersName": "",
      "mothersName": "",
      "lastScore": "85%",
      "dialogOpen": false
    },
    {
      "id": "txz-I6u",
      "studentName": "Arun",
      "category": "International",
      "domicileDoc": true,
      "birthDoc": true,
      "marksheetDoc": true,
      "policeClearanceDoc": true,
      "passportDoc": true,
      "declarationDoc": true,
      "dob": "1997-09-19",
      "fathersName": "",
      "mothersName": "",
      "lastScore": "95%",
      "dialogOpen": false
    },
    {
      "id": "jDeK4wB",
      "studentName": "Abhinav",
      "category": "International",
      "domicileDoc": true,
      "birthDoc": true,
      "marksheetDoc": true,
      "policeClearanceDoc": true,
      "passportDoc": true,
      "declarationDoc": true,
      "dob": "2002-01-21",
      "fathersName": "",
      "mothersName": "",
      "lastScore": "76%",
      "dialogOpen": false
    },
    {
      "id": "PMXo6tK",
      "studentName": "Priyanka",
      "category": "Domestic",
      "domicileDoc": true,
      "birthDoc": true,
      "marksheetDoc": true,
      "policeClearanceDoc": false,
      "passportDoc": false,
      "declarationDoc": true,
      "dob": "1998-11-17",
      "fathersName": "",
      "mothersName": "",
      "lastScore": "89%",
      "dialogOpen": false
    },
    {
      "id": "gwSiYcV",
      "studentName": "Harshith",
      "category": "Domestic",
      "domicileDoc": true,
      "birthDoc": true,
      "marksheetDoc": true,
      "policeClearanceDoc": false,
      "passportDoc": false,
      "declarationDoc": true,
      "dob": "1998-12-09",
      "fathersName": "",
      "mothersName": "",
      "lastScore": "78%",
      "dialogOpen": false
    },
    {
      "id": "Z3_caIY",
      "studentName": "Divya",
      "category": "International",
      "domicileDoc": true,
      "birthDoc": true,
      "marksheetDoc": true,
      "policeClearanceDoc": true,
      "passportDoc": true,
      "declarationDoc": true,
      "dob": "1999-12-25",
      "fathersName": "",
      "mothersName": "",
      "lastScore": "88%",
      "dialogOpen": false
    },
    {
      "id": "L8jXyTC",
      "studentName": "Sruthi",
      "category": "International",
      "domicileDoc": true,
      "birthDoc": true,
      "marksheetDoc": true,
      "policeClearanceDoc": true,
      "passportDoc": true,
      "declarationDoc": true,
      "dob": "1998-11-19",
      "fathersName": "",
      "mothersName": "",
      "lastScore": "91%",
      "dialogOpen": false
    }
  ]
}